LICENSE
mkfbr/__init__.py
mkfbr/database/address.db
mkfbr/generators.py
mkfbr/json/content.json
mkfbr/mkfbr.py
mkfbr/models.py
mkfbr-0.1.7.dist-info/LICENSE
mkfbr-0.1.7.dist-info/WHEEL
mkfbr-0.1.7.dist-info/METADATA
mkfbr-0.1.7.dist-info/RECORD
