Metadata-Version: 2.1
Name: mkfbr
Version: 0.1.7
Summary: This simple project only serves as an object of study and/or software testing, do not use it for fraudulent activities.
Home-page: https://github.com/darkmathew/make_a_fake_brazilian
License: MIT
Author: Matheus Santos
Author-email: 78329418+darkmathew@users.noreply.github.com
Requires-Python: >=3.10,<4.0
Classifier: License :: OSI Approved :: MIT License
Classifier: Programming Language :: Python :: 3
Classifier: Programming Language :: Python :: 3.10
Project-URL: Repository, https://github.com/darkmathew/make_a_fake_brazilian
